gloves/__init__.py
gloves-0.1.0.dist-info/WHEEL
gloves-0.1.0.dist-info/METADATA
gloves-0.1.0.dist-info/RECORD
