Metadata-Version: 2.1
Name: gloves
Version: 0.1.0
Summary: this project is a demonstration of a strategy for creating packages with Poetry, python-semantic-release and commitzen
Author: Leonardo Pires
Author-email: leonardorifiol.p@gmail.com
Requires-Python: >=3.8,<4.0
Classifier: Programming Language :: Python :: 3
Classifier: Programming Language :: Python :: 3.8
Classifier: Programming Language :: Python :: 3.9
Classifier: Programming Language :: Python :: 3.10
Requires-Dist: poetry (>=1.2.1,<2.0.0)
